just/__init__.py
just/bytes.py
just/csv_.py
just/date.py
just/dir.py
just/dt.py
just/forcedip.py
just/jpath.py
just/json_.py
just/log.py
just/newl.py
just/path_.py
just/pattern.py
just/pickle_.py
just/read_write.py
just/requests_.py
just/source_ip.py
just/toml_.py
just/txt.py
just/yaml_.py
just/zstd_.py
just-0.8.163.dist-info/LICENSE
just-0.8.163.dist-info/METADATA
just-0.8.163.dist-info/WHEEL
just-0.8.163.dist-info/entry_points.txt
just-0.8.163.dist-info/top_level.txt
just-0.8.163.dist-info/RECORD
